lab_1/collatz.sv
module collatz( input logic         clk,   // Clock
		input logic 	    go,    // Load value from n; start iterating
		input logic  [31:0] n,     // Start value; only read when go = 1
		output logic [31:0] dout,  // Iteration value: true after go = 1
		output logic 	    done); // True when dout reaches 1

   // done is true whenever dout has reached 1
   always_comb begin
      done = (dout == 32'd1);
   end

   always_ff @(posedge clk) begin
      if (go) begin
         // Restart sequence from n
         dout <= n;
      end else begin
         // Iterate once per clock until reaching 1
         if (dout != 32'd1) begin
            if (dout[0] == 1'b0) begin
               // even: n = n/2
               dout <= (dout >> 1);
            end else begin
               // odd: n = 3n + 1  (shift/add)
               dout <= (dout << 1) + dout + 32'd1;
            end
         end
      end
   end

endmodule

lab_1/range.sv
module range
   #(parameter
     RAM_WORDS = 16,            // Number of counts to store in RAM
     RAM_ADDR_BITS = 4)         // Number of RAM address bits
   (input  logic         clk,    // Clock
    input  logic         go,     // Read start and start testing
    input  logic [31:0]  start,  // Number to start from or count to read
    output logic         done,   // True once memory is filled
    output logic [15:0]  count); // Iteration count once finished

   logic        cgo;    // "go" for the Collatz iterator
   logic        cdone;  // "done" from the Collatz iterator
   logic [31:0] n;      // number to start the Collatz iterator

   // verilator lint_off PINCONNECTEMPTY
   collatz c1(.clk(clk),
              .go(cgo),
              .n(n),
              .done(cdone),
              .dout());

   logic [RAM_ADDR_BITS-1:0] num;     // RAM address to write
   logic                     running; // True during iterations

   logic                     we;      // Write enable
   logic [15:0]              din;
   logic [15:0]              mem[RAM_WORDS-1:0];
   logic [RAM_ADDR_BITS-1:0] addr;

   // Edge detectors
   logic go_d, cdone_d;
   wire  go_rise    = go    & ~go_d;
   wire  cdone_rise = cdone & ~cdone_d;

   // Write exactly once when cdone rises
   assign we = running & cdone_rise;

   // -----------------------------
   // No-FSM control (robust launch)
   // -----------------------------
   always_ff @(posedge clk) begin
      // track edges
      go_d    <= go;
      cdone_d <= cdone;

      // default: no pulse
      cgo <= 1'b0;

      // Start new sweep on go rising edge
      if (go_rise) begin
         running        <= 1'b1;
         cgo           <= 1'b1;
         done           <= 1'b0;
         num            <= '0;
         n              <= start;
         din            <= 16'd1;      
      end
      else if (running) begin
         // Count cycles only after launch has happened and before done
         if (!cgo && !cdone) begin
            din <= din + 16'd1;
         end

         // On completion (one time), advance / finish
         if (cdone_rise) begin
            if (num == RAM_ADDR_BITS'(RAM_WORDS-1)) begin
               running <= 1'b0;
               done    <= 1'b1;
            end
            else begin
               num            <= num + 1'b1;
               n              <= n + 32'd1;
               din            <= 16'd1;
               cgo           <= 1'b1;       
            end
         end
      end
   end 

   // -----------------------------
   // RAM read/write
   // -----------------------------
   assign addr = we ? num : start[RAM_ADDR_BITS-1:0];

   always_ff @(posedge clk) begin
      if (we) mem[addr] <= din;
      count <= mem[addr];
   end

endmodule

lab_1/range.vcd
$version Generated by VerilatedVcd $end
$timescale 1ps $end
 $scope module TOP $end
  $var wire 1 > clk $end
  $var wire 1 ? go $end
  $var wire 32 @ start [31:0] $end
  $var wire 1 A done $end
  $var wire 16 B count [15:0] $end
  $scope module range $end
   $var wire 32 E RAM_WORDS [31:0] $end
   $var wire 32 F RAM_ADDR_BITS [31:0] $end
   $var wire 1 > clk $end
   $var wire 1 ? go $end
   $var wire 32 @ start [31:0] $end
   $var wire 1 A done $end
   $var wire 16 B count [15:0] $end
   $var wire 1 # cgo $end
   $var wire 1 $ cdone $end
   $var wire 32 % n [31:0] $end
   $var wire 4 & num [3:0] $end
   $var wire 1 ' running $end
   $var wire 1 ( we $end
   $var wire 16 ) din [15:0] $end
   $var wire 16 * mem[0] [15:0] $end
   $var wire 16 + mem[1] [15:0] $end
   $var wire 16 , mem[2] [15:0] $end
   $var wire 16 - mem[3] [15:0] $end
   $var wire 16 . mem[4] [15:0] $end
   $var wire 16 / mem[5] [15:0] $end
   $var wire 16 0 mem[6] [15:0] $end
   $var wire 16 1 mem[7] [15:0] $end
   $var wire 16 2 mem[8] [15:0] $end
   $var wire 16 3 mem[9] [15:0] $end
   $var wire 16 4 mem[10] [15:0] $end
   $var wire 16 5 mem[11] [15:0] $end
   $var wire 16 6 mem[12] [15:0] $end
   $var wire 16 7 mem[13] [15:0] $end
   $var wire 16 8 mem[14] [15:0] $end
   $var wire 16 9 mem[15] [15:0] $end
   $var wire 4 C addr [3:0] $end
   $var wire 1 : go_d $end
   $var wire 1 ; cdone_d $end
   $var wire 1 D go_rise $end
   $var wire 1 < cdone_rise $end
   $scope module c1 $end
    $var wire 1 > clk $end
    $var wire 1 # go $end
    $var wire 32 % n [31:0] $end
    $var wire 32 = dout [31:0] $end
    $var wire 1 $ done $end
   $upscope $end
  $upscope $end
 $upscope $end
$enddefinitions $end


#0
0#
0$
b00000000000000000000000000000000 %
b0000 &
0'
0(
b0000000000000000 )
b0000000000000000 *
b0000000000000000 +
b0000000000000000 ,
b0000000000000000 -
b0000000000000000 .
b0000000000000000 /
b0000000000000000 0
b0000000000000000 1
b0000000000000000 2
b0000000000000000 3
b0000000000000000 4
b0000000000000000 5
b0000000000000000 6
b0000000000000000 7
b0000000000000000 8
b0000000000000000 9
0:
0;
0<
b00000000000000000000000000000000 =
0>
1?
b00000000000000000000000000000111 @
0A
b0000000000000000 B
b0111 C
1D
b00000000000000000000000000010000 E
b00000000000000000000000000000100 F
#10
1#
b00000000000000000000000000000111 %
1'
b0000000000000001 )
1:
1>
0D
#20
0>
#30
0#
b00000000000000000000000000000111 =
1>
#40
0>
0?
#50
b0000000000000010 )
0:
b00000000000000000000000000010110 =
1>
#60
0>
#70
b0000000000000011 )
b00000000000000000000000000001011 =
1>
#80
0>
#90
b0000000000000100 )
b00000000000000000000000000100010 =
1>
#100
0>
#110
b0000000000000101 )
b00000000000000000000000000010001 =
1>
#120
0>
#130
b0000000000000110 )
b00000000000000000000000000110100 =
1>
#140
0>
#150
b0000000000000111 )
b00000000000000000000000000011010 =
1>
#160
0>
#170
b0000000000001000 )
b00000000000000000000000000001101 =
1>
#180
0>
#190
b0000000000001001 )
b00000000000000000000000000101000 =
1>
#200
0>
#210
b0000000000001010 )
b00000000000000000000000000010100 =
1>
#220
0>
#230
b0000000000001011 )
b00000000000000000000000000001010 =
1>
#240
0>
#250
b0000000000001100 )
b00000000000000000000000000000101 =
1>
#260
0>
#270
b0000000000001101 )
b00000000000000000000000000010000 =
1>
#280
0>
#290
b0000000000001110 )
b00000000000000000000000000001000 =
1>
#300
0>
#310
b0000000000001111 )
b00000000000000000000000000000100 =
1>
#320
0>
#330
b0000000000010000 )
b00000000000000000000000000000010 =
1>
#340
0>
#350
1$
1(
b0000000000010001 )
1<
b00000000000000000000000000000001 =
1>
b0000 C
#360
0>
#370
1#
b00000000000000000000000000001000 %
b0001 &
0(
b0000000000000001 )
b0000000000010001 *
1;
0<
1>
b0111 C
#380
0>
#390
0#
0$
b00000000000000000000000000001000 =
1>
#400
0>
#410
b0000000000000010 )
0;
b00000000000000000000000000000100 =
1>
#420
0>
#430
b0000000000000011 )
b00000000000000000000000000000010 =
1>
#440
0>
#450
1$
1(
b0000000000000100 )
1<
b00000000000000000000000000000001 =
1>
b0001 C
#460
0>
#470
1#
b00000000000000000000000000001001 %
b0010 &
0(
b0000000000000001 )
b0000000000000100 +
1;
0<
1>
b0111 C
#480
0>
#490
0#
0$
b00000000000000000000000000001001 =
1>
#500
0>
#510
b0000000000000010 )
0;
b00000000000000000000000000011100 =
1>
#520
0>
#530
b0000000000000011 )
b00000000000000000000000000001110 =
1>
#540
0>
#550
b0000000000000100 )
b00000000000000000000000000000111 =
1>
#560
0>
#570
b0000000000000101 )
b00000000000000000000000000010110 =
1>
#580
0>
#590
b0000000000000110 )
b00000000000000000000000000001011 =
1>
#600
0>
#610
b0000000000000111 )
b00000000000000000000000000100010 =
1>
#620
0>
#630
b0000000000001000 )
b00000000000000000000000000010001 =
1>
#640
0>
#650
b0000000000001001 )
b00000000000000000000000000110100 =
1>
#660
0>
#670
b0000000000001010 )
b00000000000000000000000000011010 =
1>
#680
0>
#690
b0000000000001011 )
b00000000000000000000000000001101 =
1>
#700
0>
#710
b0000000000001100 )
b00000000000000000000000000101000 =
1>
#720
0>
#730
b0000000000001101 )
b00000000000000000000000000010100 =
1>
#740
0>
#750
b0000000000001110 )
b00000000000000000000000000001010 =
1>
#760
0>
#770
b0000000000001111 )
b00000000000000000000000000000101 =
1>
#780
0>
#790
b0000000000010000 )
b00000000000000000000000000010000 =
1>
#800
0>
#810
b0000000000010001 )
b00000000000000000000000000001000 =
1>
#820
0>
#830
b0000000000010010 )
b00000000000000000000000000000100 =
1>
#840
0>
#850
b0000000000010011 )
b00000000000000000000000000000010 =
1>
#860
0>
#870
1$
1(
b0000000000010100 )
1<
b00000000000000000000000000000001 =
1>
b0010 C
#880
0>
#890
1#
b00000000000000000000000000001010 %
b0011 &
0(
b0000000000000001 )
b0000000000010100 ,
1;
0<
1>
b0111 C
#900
0>
#910
0#
0$
b00000000000000000000000000001010 =
1>
#920
0>
#930
b0000000000000010 )
0;
b00000000000000000000000000000101 =
1>
#940
0>
#950
b0000000000000011 )
b00000000000000000000000000010000 =
1>
#960
0>
#970
b0000000000000100 )
b00000000000000000000000000001000 =
1>
#980
0>
#990
b0000000000000101 )
b00000000000000000000000000000100 =
1>
#1000
0>
#1010
b0000000000000110 )
b00000000000000000000000000000010 =
1>
#1020
0>
#1030
1$
1(
b0000000000000111 )
1<
b00000000000000000000000000000001 =
1>
b0011 C
#1040
0>
#1050
1#
b00000000000000000000000000001011 %
b0100 &
0(
b0000000000000001 )
b0000000000000111 -
1;
0<
1>
b0111 C
#1060
0>
#1070
0#
0$
b00000000000000000000000000001011 =
1>
#1080
0>
#1090
b0000000000000010 )
0;
b00000000000000000000000000100010 =
1>
#1100
0>
#1110
b0000000000000011 )
b00000000000000000000000000010001 =
1>
#1120
0>
#1130
b0000000000000100 )
b00000000000000000000000000110100 =
1>
#1140
0>
#1150
b0000000000000101 )
b00000000000000000000000000011010 =
1>
#1160
0>
#1170
b0000000000000110 )
b00000000000000000000000000001101 =
1>
#1180
0>
#1190
b0000000000000111 )
b00000000000000000000000000101000 =
1>
#1200
0>
#1210
b0000000000001000 )
b00000000000000000000000000010100 =
1>
#1220
0>
#1230
b0000000000001001 )
b00000000000000000000000000001010 =
1>
#1240
0>
#1250
b0000000000001010 )
b00000000000000000000000000000101 =
1>
#1260
0>
#1270
b0000000000001011 )
b00000000000000000000000000010000 =
1>
#1280
0>
#1290
b0000000000001100 )
b00000000000000000000000000001000 =
1>
#1300
0>
#1310
b0000000000001101 )
b00000000000000000000000000000100 =
1>
#1320
0>
#1330
b0000000000001110 )
b00000000000000000000000000000010 =
1>
#1340
0>
#1350
1$
1(
b0000000000001111 )
1<
b00000000000000000000000000000001 =
1>
b0100 C
#1360
0>
#1370
1#
b00000000000000000000000000001100 %
b0101 &
0(
b0000000000000001 )
b0000000000001111 .
1;
0<
1>
b0111 C
#1380
0>
#1390
0#
0$
b00000000000000000000000000001100 =
1>
#1400
0>
#1410
b0000000000000010 )
0;
b00000000000000000000000000000110 =
1>
#1420
0>
#1430
b0000000000000011 )
b00000000000000000000000000000011 =
1>
#1440
0>
#1450
b0000000000000100 )
b00000000000000000000000000001010 =
1>
#1460
0>
#1470
b0000000000000101 )
b00000000000000000000000000000101 =
1>
#1480
0>
#1490
b0000000000000110 )
b00000000000000000000000000010000 =
1>
#1500
0>
#1510
b0000000000000111 )
b00000000000000000000000000001000 =
1>
#1520
0>
#1530
b0000000000001000 )
b00000000000000000000000000000100 =
1>
#1540
0>
#1550
b0000000000001001 )
b00000000000000000000000000000010 =
1>
#1560
0>
#1570
1$
1(
b0000000000001010 )
1<
b00000000000000000000000000000001 =
1>
b0101 C
#1580
0>
#1590
1#
b00000000000000000000000000001101 %
b0110 &
0(
b0000000000000001 )
b0000000000001010 /
1;
0<
1>
b0111 C
#1600
0>
#1610
0#
0$
b00000000000000000000000000001101 =
1>
#1620
0>
#1630
b0000000000000010 )
0;
b00000000000000000000000000101000 =
1>
#1640
0>
#1650
b0000000000000011 )
b00000000000000000000000000010100 =
1>
#1660
0>
#1670
b0000000000000100 )
b00000000000000000000000000001010 =
1>
#1680
0>
#1690
b0000000000000101 )
b00000000000000000000000000000101 =
1>
#1700
0>
#1710
b0000000000000110 )
b00000000000000000000000000010000 =
1>
#1720
0>
#1730
b0000000000000111 )
b00000000000000000000000000001000 =
1>
#1740
0>
#1750
b0000000000001000 )
b00000000000000000000000000000100 =
1>
#1760
0>
#1770
b0000000000001001 )
b00000000000000000000000000000010 =
1>
#1780
0>
#1790
1$
1(
b0000000000001010 )
1<
b00000000000000000000000000000001 =
1>
b0110 C
#1800
0>
#1810
1#
b00000000000000000000000000001110 %
b0111 &
0(
b0000000000000001 )
b0000000000001010 0
1;
0<
1>
b0111 C
#1820
0>
#1830
0#
0$
b00000000000000000000000000001110 =
1>
#1840
0>
#1850
b0000000000000010 )
0;
b00000000000000000000000000000111 =
1>
#1860
0>
#1870
b0000000000000011 )
b00000000000000000000000000010110 =
1>
#1880
0>
#1890
b0000000000000100 )
b00000000000000000000000000001011 =
1>
#1900
0>
#1910
b0000000000000101 )
b00000000000000000000000000100010 =
1>
#1920
0>
#1930
b0000000000000110 )
b00000000000000000000000000010001 =
1>
#1940
0>
#1950
b0000000000000111 )
b00000000000000000000000000110100 =
1>
#1960
0>
#1970
b0000000000001000 )
b00000000000000000000000000011010 =
1>
#1980
0>
#1990
b0000000000001001 )
b00000000000000000000000000001101 =
1>
#2000
0>
#2010
b0000000000001010 )
b00000000000000000000000000101000 =
1>
#2020
0>
#2030
b0000000000001011 )
b00000000000000000000000000010100 =
1>
#2040
0>
#2050
b0000000000001100 )
b00000000000000000000000000001010 =
1>
#2060
0>
#2070
b0000000000001101 )
b00000000000000000000000000000101 =
1>
#2080
0>
#2090
b0000000000001110 )
b00000000000000000000000000010000 =
1>
#2100
0>
#2110
b0000000000001111 )
b00000000000000000000000000001000 =
1>
#2120
0>
#2130
b0000000000010000 )
b00000000000000000000000000000100 =
1>
#2140
0>
#2150
b0000000000010001 )
b00000000000000000000000000000010 =
1>
#2160
0>
#2170
1$
1(
b0000000000010010 )
1<
b00000000000000000000000000000001 =
1>
#2180
0>
#2190
1#
b00000000000000000000000000001111 %
b1000 &
0(
b0000000000000001 )
b0000000000010010 1
1;
0<
1>
#2200
0>
#2210
0#
0$
b00000000000000000000000000001111 =
1>
b0000000000010010 B
#2220
0>
#2230
b0000000000000010 )
0;
b00000000000000000000000000101110 =
1>
#2240
0>
#2250
b0000000000000011 )
b00000000000000000000000000010111 =
1>
#2260
0>
#2270
b0000000000000100 )
b00000000000000000000000001000110 =
1>
#2280
0>
#2290
b0000000000000101 )
b00000000000000000000000000100011 =
1>
#2300
0>
#2310
b0000000000000110 )
b00000000000000000000000001101010 =
1>
#2320
0>
#2330
b0000000000000111 )
b00000000000000000000000000110101 =
1>
#2340
0>
#2350
b0000000000001000 )
b00000000000000000000000010100000 =
1>
#2360
0>
#2370
b0000000000001001 )
b00000000000000000000000001010000 =
1>
#2380
0>
#2390
b0000000000001010 )
b00000000000000000000000000101000 =
1>
#2400
0>
#2410
b0000000000001011 )
b00000000000000000000000000010100 =
1>
#2420
0>
#2430
b0000000000001100 )
b00000000000000000000000000001010 =
1>
#2440
0>
#2450
b0000000000001101 )
b00000000000000000000000000000101 =
1>
#2460
0>
#2470
b0000000000001110 )
b00000000000000000000000000010000 =
1>
#2480
0>
#2490
b0000000000001111 )
b00000000000000000000000000001000 =
1>
#2500
0>
#2510
b0000000000010000 )
b00000000000000000000000000000100 =
1>
#2520
0>
#2530
b0000000000010001 )
b00000000000000000000000000000010 =
1>
#2540
0>
#2550
1$
1(
b0000000000010010 )
1<
b00000000000000000000000000000001 =
1>
b1000 C
#2560
0>
#2570
1#
b00000000000000000000000000010000 %
b1001 &
0(
b0000000000000001 )
b0000000000010010 2
1;
0<
1>
b0000000000000000 B
b0111 C
#2580
0>
#2590
0#
0$
b00000000000000000000000000010000 =
1>
b0000000000010010 B
#2600
0>
#2610
b0000000000000010 )
0;
b00000000000000000000000000001000 =
1>
#2620
0>
#2630
b0000000000000011 )
b00000000000000000000000000000100 =
1>
#2640
0>
#2650
b0000000000000100 )
b00000000000000000000000000000010 =
1>
#2660
0>
#2670
1$
1(
b0000000000000101 )
1<
b00000000000000000000000000000001 =
1>
b1001 C
#2680
0>
#2690
1#
b00000000000000000000000000010001 %
b1010 &
0(
b0000000000000001 )
b0000000000000101 3
1;
0<
1>
b0000000000000000 B
b0111 C
#2700
0>
#2710
0#
0$
b00000000000000000000000000010001 =
1>
b0000000000010010 B
#2720
0>
#2730
b0000000000000010 )
0;
b00000000000000000000000000110100 =
1>
#2740
0>
#2750
b0000000000000011 )
b00000000000000000000000000011010 =
1>
#2760
0>
#2770
b0000000000000100 )
b00000000000000000000000000001101 =
1>
#2780
0>
#2790
b0000000000000101 )
b00000000000000000000000000101000 =
1>
#2800
0>
#2810
b0000000000000110 )
b00000000000000000000000000010100 =
1>
#2820
0>
#2830
b0000000000000111 )
b00000000000000000000000000001010 =
1>
#2840
0>
#2850
b0000000000001000 )
b00000000000000000000000000000101 =
1>
#2860
0>
#2870
b0000000000001001 )
b00000000000000000000000000010000 =
1>
#2880
0>
#2890
b0000000000001010 )
b00000000000000000000000000001000 =
1>
#2900
0>
#2910
b0000000000001011 )
b00000000000000000000000000000100 =
1>
#2920
0>
#2930
b0000000000001100 )
b00000000000000000000000000000010 =
1>
#2940
0>
#2950
1$
1(
b0000000000001101 )
1<
b00000000000000000000000000000001 =
1>
b1010 C
#2960
0>
#2970
1#
b00000000000000000000000000010010 %
b1011 &
0(
b0000000000000001 )
b0000000000001101 4
1;
0<
1>
b0000000000000000 B
b0111 C
#2980
0>
#2990
0#
0$
b00000000000000000000000000010010 =
1>
b0000000000010010 B
#3000
0>
#3010
b0000000000000010 )
0;
b00000000000000000000000000001001 =
1>
#3020
0>
#3030
b0000000000000011 )
b00000000000000000000000000011100 =
1>
#3040
0>
#3050
b0000000000000100 )
b00000000000000000000000000001110 =
1>
#3060
0>
#3070
b0000000000000101 )
b00000000000000000000000000000111 =
1>
#3080
0>
#3090
b0000000000000110 )
b00000000000000000000000000010110 =
1>
#3100
0>
#3110
b0000000000000111 )
b00000000000000000000000000001011 =
1>
#3120
0>
#3130
b0000000000001000 )
b00000000000000000000000000100010 =
1>
#3140
0>
#3150
b0000000000001001 )
b00000000000000000000000000010001 =
1>
#3160
0>
#3170
b0000000000001010 )
b00000000000000000000000000110100 =
1>
#3180
0>
#3190
b0000000000001011 )
b00000000000000000000000000011010 =
1>
#3200
0>
#3210
b0000000000001100 )
b00000000000000000000000000001101 =
1>
#3220
0>
#3230
b0000000000001101 )
b00000000000000000000000000101000 =
1>
#3240
0>
#3250
b0000000000001110 )
b00000000000000000000000000010100 =
1>
#3260
0>
#3270
b0000000000001111 )
b00000000000000000000000000001010 =
1>
#3280
0>
#3290
b0000000000010000 )
b00000000000000000000000000000101 =
1>
#3300
0>
#3310
b0000000000010001 )
b00000000000000000000000000010000 =
1>
#3320
0>
#3330
b0000000000010010 )
b00000000000000000000000000001000 =
1>
#3340
0>
#3350
b0000000000010011 )
b00000000000000000000000000000100 =
1>
#3360
0>
#3370
b0000000000010100 )
b00000000000000000000000000000010 =
1>
#3380
0>
#3390
1$
1(
b0000000000010101 )
1<
b00000000000000000000000000000001 =
1>
b1011 C
#3400
0>
#3410
1#
b00000000000000000000000000010011 %
b1100 &
0(
b0000000000000001 )
b0000000000010101 5
1;
0<
1>
b0000000000000000 B
b0111 C
#3420
0>
#3430
0#
0$
b00000000000000000000000000010011 =
1>
b0000000000010010 B
#3440
0>
#3450
b0000000000000010 )
0;
b00000000000000000000000000111010 =
1>
#3460
0>
#3470
b0000000000000011 )
b00000000000000000000000000011101 =
1>
#3480
0>
#3490
b0000000000000100 )
b00000000000000000000000001011000 =
1>
#3500
0>
#3510
b0000000000000101 )
b00000000000000000000000000101100 =
1>
#3520
0>
#3530
b0000000000000110 )
b00000000000000000000000000010110 =
1>
#3540
0>
#3550
b0000000000000111 )
b00000000000000000000000000001011 =
1>
#3560
0>
#3570
b0000000000001000 )
b00000000000000000000000000100010 =
1>
#3580
0>
#3590
b0000000000001001 )
b00000000000000000000000000010001 =
1>
#3600
0>
#3610
b0000000000001010 )
b00000000000000000000000000110100 =
1>
#3620
0>
#3630
b0000000000001011 )
b00000000000000000000000000011010 =
1>
#3640
0>
#3650
b0000000000001100 )
b00000000000000000000000000001101 =
1>
#3660
0>
#3670
b0000000000001101 )
b00000000000000000000000000101000 =
1>
#3680
0>
#3690
b0000000000001110 )
b00000000000000000000000000010100 =
1>
#3700
0>
#3710
b0000000000001111 )
b00000000000000000000000000001010 =
1>
#3720
0>
#3730
b0000000000010000 )
b00000000000000000000000000000101 =
1>
#3740
0>
#3750
b0000000000010001 )
b00000000000000000000000000010000 =
1>
#3760
0>
#3770
b0000000000010010 )
b00000000000000000000000000001000 =
1>
#3780
0>
#3790
b0000000000010011 )
b00000000000000000000000000000100 =
1>
#3800
0>
#3810
b0000000000010100 )
b00000000000000000000000000000010 =
1>
#3820
0>
#3830
1$
1(
b0000000000010101 )
1<
b00000000000000000000000000000001 =
1>
b1100 C
#3840
0>
#3850
1#
b00000000000000000000000000010100 %
b1101 &
0(
b0000000000000001 )
b0000000000010101 6
1;
0<
1>
b0000000000000000 B
b0111 C
#3860
0>
#3870
0#
0$
b00000000000000000000000000010100 =
1>
b0000000000010010 B
#3880
0>
#3890
b0000000000000010 )
0;
b00000000000000000000000000001010 =
1>
#3900
0>
#3910
b0000000000000011 )
b00000000000000000000000000000101 =
1>
#3920
0>
#3930
b0000000000000100 )
b00000000000000000000000000010000 =
1>
#3940
0>
#3950
b0000000000000101 )
b00000000000000000000000000001000 =
1>
#3960
0>
#3970
b0000000000000110 )
b00000000000000000000000000000100 =
1>
#3980
0>
#3990
b0000000000000111 )
b00000000000000000000000000000010 =
1>
#4000
0>
#4010
1$
1(
b0000000000001000 )
1<
b00000000000000000000000000000001 =
1>
b1101 C
#4020
0>
#4030
1#
b00000000000000000000000000010101 %
b1110 &
0(
b0000000000000001 )
b0000000000001000 7
1;
0<
1>
b0000000000000000 B
b0111 C
#4040
0>
#4050
0#
0$
b00000000000000000000000000010101 =
1>
b0000000000010010 B
#4060
0>
#4070
b0000000000000010 )
0;
b00000000000000000000000001000000 =
1>
#4080
0>
#4090
b0000000000000011 )
b00000000000000000000000000100000 =
1>
#4100
0>
#4110
b0000000000000100 )
b00000000000000000000000000010000 =
1>
#4120
0>
#4130
b0000000000000101 )
b00000000000000000000000000001000 =
1>
#4140
0>
#4150
b0000000000000110 )
b00000000000000000000000000000100 =
1>
#4160
0>
#4170
b0000000000000111 )
b00000000000000000000000000000010 =
1>
#4180
0>
#4190
1$
1(
b0000000000001000 )
1<
b00000000000000000000000000000001 =
1>
b1110 C
#4200
0>
#4210
1#
b00000000000000000000000000010110 %
b1111 &
0(
b0000000000000001 )
b0000000000001000 8
1;
0<
1>
b0000000000000000 B
b0111 C
#4220
0>
#4230
0#
0$
b00000000000000000000000000010110 =
1>
b0000000000010010 B
#4240
0>
#4250
b0000000000000010 )
0;
b00000000000000000000000000001011 =
1>
#4260
0>
#4270
b0000000000000011 )
b00000000000000000000000000100010 =
1>
#4280
0>
#4290
b0000000000000100 )
b00000000000000000000000000010001 =
1>
#4300
0>
#4310
b0000000000000101 )
b00000000000000000000000000110100 =
1>
#4320
0>
#4330
b0000000000000110 )
b00000000000000000000000000011010 =
1>
#4340
0>
#4350
b0000000000000111 )
b00000000000000000000000000001101 =
1>
#4360
0>
#4370
b0000000000001000 )
b00000000000000000000000000101000 =
1>
#4380
0>
#4390
b0000000000001001 )
b00000000000000000000000000010100 =
1>
#4400
0>
#4410
b0000000000001010 )
b00000000000000000000000000001010 =
1>
#4420
0>
#4430
b0000000000001011 )
b00000000000000000000000000000101 =
1>
#4440
0>
#4450
b0000000000001100 )
b00000000000000000000000000010000 =
1>
#4460
0>
#4470
b0000000000001101 )
b00000000000000000000000000001000 =
1>
#4480
0>
#4490
b0000000000001110 )
b00000000000000000000000000000100 =
1>
#4500
0>
#4510
b0000000000001111 )
b00000000000000000000000000000010 =
1>
#4520
0>
#4530
1$
1(
b0000000000010000 )
1<
b00000000000000000000000000000001 =
1>
b1111 C
#4540
0>
#4550
0'
0(
b0000000000010000 9
1;
0<
1>
1A
b0000000000000000 B
b0111 C
#4560
0>
b00000000000000000000000000000000 @
b0000 C
#4570
1>
b0000000000010001 B
#4580
0>
b00000000000000000000000000000001 @
b0001 C
#4590
1>
b0000000000000100 B
#4600
0>
b00000000000000000000000000000010 @
b0010 C
#4610
1>
b0000000000010100 B
#4620
0>
b00000000000000000000000000000011 @
b0011 C
#4630
1>
b0000000000000111 B
#4640
0>
b00000000000000000000000000000100 @
b0100 C
#4650
1>
b0000000000001111 B
#4660
0>
b00000000000000000000000000000101 @
b0101 C
#4670
1>
b0000000000001010 B
#4680
0>
b00000000000000000000000000000110 @
b0110 C
#4690
1>
#4700
0>
b00000000000000000000000000000111 @
b0111 C
#4710
1>
b0000000000010010 B
#4720
0>
b00000000000000000000000000001000 @
b1000 C
#4730
1>
#4740
0>
b00000000000000000000000000001001 @
b1001 C
#4750
1>
b0000000000000101 B
#4760
0>
b00000000000000000000000000001010 @
b1010 C
#4770
1>
b0000000000001101 B
#4780
0>
b00000000000000000000000000001011 @
b1011 C
#4790
1>
b0000000000010101 B
#4800
0>
b00000000000000000000000000001100 @
b1100 C
#4810
1>
#4820
0>
b00000000000000000000000000001101 @
b1101 C
#4830
1>
b0000000000001000 B
#4840
0>
b00000000000000000000000000001110 @
b1110 C
#4850
1>
#4860
0>
b00000000000000000000000000001111 @
b1111 C
#4870
1>
b0000000000010000 B
